speedywalk-0.4.0.dist-info/METADATA
speedywalk-0.4.0.dist-info/WHEEL
speedywalk-0.4.0.dist-info/licenses/LICENSE
speedywalk/__init__.py
speedywalk/_core.cpython-312-aarch64-linux-gnu.so
speedywalk/py.typed
speedywalk-0.4.0.dist-info/RECORD
