Metadata-Version: 2.4
Name: speedywalk
Version: 0.4.0
Classifier: Development Status :: 4 - Beta
Classifier: Intended Audience :: Developers
Classifier: License :: OSI Approved :: MIT License
Classifier: Programming Language :: Python :: 3
Classifier: Programming Language :: Python :: 3.10
Classifier: Programming Language :: Python :: 3.11
Classifier: Programming Language :: Python :: 3.12
Classifier: Programming Language :: Python :: 3.13
Classifier: Programming Language :: Rust
Classifier: Programming Language :: Python :: Implementation :: CPython
Classifier: Programming Language :: Python :: Implementation :: PyPy
Classifier: Topic :: Software Development :: Libraries :: Python Modules
Classifier: Topic :: System :: Filesystems
License-File: LICENSE
Summary: Fast parallel directory walking for Python, powered by Rust
Keywords: filesystem,directory,walk,parallel,fast,gitignore
Author: Peter Byfield
Requires-Python: >=3.10
Project-URL: Homepage, https://peter554.github.io/speedywalk/
Project-URL: Repository, https://github.com/Peter554/speedywalk
Project-URL: Issues, https://github.com/Peter554/speedywalk/issues
Project-URL: Documentation, https://peter554.github.io/speedywalk/
